model_clf/__init__.py
model_clf/help.py
model_clf/model_config_loader.py
model_clf/model_param_grid.py
model_clf/setup.py
model_clf/utils.py
models_classifier-0.1.1.dist-info/licenses/LICENSE
models_classifier-0.1.1.dist-info/METADATA
models_classifier-0.1.1.dist-info/WHEEL
models_classifier-0.1.1.dist-info/top_level.txt
models_classifier-0.1.1.dist-info/RECORD
