Metadata-Version: 2.4
Name: models-classifier
Version: 0.1.1
Summary: A flexible classification training module with SHAP and ROC analysis
Author: wangwei
Author-email: wangwei <wangwei@siat.ac.cn>
Requires-Python: >=3.8
License-File: LICENSE
Requires-Dist: numpy
Requires-Dist: jupyter
Requires-Dist: pandas
Requires-Dist: scikit-learn
Requires-Dist: matplotlib
Requires-Dist: shap
Requires-Dist: xgboost
Requires-Dist: lightgbm
Requires-Dist: catboost
Dynamic: author
Dynamic: license-file
Dynamic: requires-python
